partial_date_time/__init__.py
partial_date_time-0.1.0.dist-info/LICENSE
partial_date_time-0.1.0.dist-info/METADATA
partial_date_time-0.1.0.dist-info/WHEEL
partial_date_time-0.1.0.dist-info/top_level.txt
partial_date_time-0.1.0.dist-info/RECORD
