Metadata-Version: 2.1
Name: partial-date-time
Version: 0.1.0
Summary: Iris PartialDateTime functionality
Home-page: https://github.com/PRIMAVERA-H2020/partial_date_time
Author: UNKNOWN
Author-email: UNKNOWN
License: UNKNOWN
Platform: UNKNOWN
